LICENSE
MANIFEST.in
README.rst
setup.py
twid/__init__.py
twid/generator.py
twid.egg-info/PKG-INFO
twid.egg-info/SOURCES.txt
twid.egg-info/dependency_links.txt
twid.egg-info/top_level.txt