Metadata-Version: 1.0
Name: twid
Version: 0.1
Summary: The relevant functions about Taiwan Identification Card system.
Home-page: UNKNOWN
Author: Plenty Su
Author-email: plenty.su@gmail.com
License: MIT
Platform: UNKNOWN
